gerapy_auto_extractor/__init__.py
gerapy_auto_extractor/__version__.py
gerapy_auto_extractor/helpers.py
gerapy_auto_extractor/settings.py
gerapy_auto_extractor/classifiers/__init__.py
gerapy_auto_extractor/classifiers/base.py
gerapy_auto_extractor/classifiers/common.py
gerapy_auto_extractor/classifiers/detail.py
gerapy_auto_extractor/classifiers/list.py
gerapy_auto_extractor/classifiers/models/list_model.pkl
gerapy_auto_extractor/classifiers/models/list_model_save.pkl
gerapy_auto_extractor/classifiers/models/list_scaler.pkl
gerapy_auto_extractor/classifiers/models/list_scaler_save.pkl
gerapy_auto_extractor/extractors/__init__.py
gerapy_auto_extractor/extractors/base.py
gerapy_auto_extractor/extractors/content.py
gerapy_auto_extractor/extractors/datetime.py
gerapy_auto_extractor/extractors/list.py
gerapy_auto_extractor/extractors/title.py
gerapy_auto_extractor/patterns/__init__.py
gerapy_auto_extractor/patterns/datetime.py
gerapy_auto_extractor/patterns/title.py
gerapy_auto_extractor/schemas/__init__.py
gerapy_auto_extractor/schemas/element.py
gerapy_auto_extractor/schemas/tag.py
gerapy_auto_extractor/utils/__init__.py
gerapy_auto_extractor/utils/cluster.py
gerapy_auto_extractor/utils/element.py
gerapy_auto_extractor/utils/helper.py
gerapy_auto_extractor/utils/lcs.py
gerapy_auto_extractor/utils/preprocess.py
gerapy_auto_extractor/utils/similarity.py
gerapy_auto_extractor_checka-0.1.1.dist-info/LICENSE
gerapy_auto_extractor_checka-0.1.1.dist-info/METADATA
gerapy_auto_extractor_checka-0.1.1.dist-info/WHEEL
gerapy_auto_extractor_checka-0.1.1.dist-info/top_level.txt
gerapy_auto_extractor_checka-0.1.1.dist-info/RECORD
