Metadata-Version: 2.1
Name: gerapy-auto-extractor-checka
Version: 0.1.1
Summary: An extractor to extract list, title, content, date, etc info without XPath or Selector
Home-page: https://github.com/aganhui/GerapyAutoExtractor_checka
Author: aganhui
Author-email: 907402005@qq.com
License: MIT
Classifier: License :: OSI Approved :: MIT License
Classifier: Programming Language :: Python :: 3.6
Classifier: Programming Language :: Python :: 3.7
Classifier: Programming Language :: Python :: 3.8
Classifier: Programming Language :: Python :: Implementation :: CPython
Classifier: Programming Language :: Python :: Implementation :: PyPy
Requires-Python: >=3.6.0
License-File: LICENSE
Requires-Dist: dateparser >=0.7.6
Requires-Dist: lxml >=4.6.5
Requires-Dist: loguru >=0.5.0
Requires-Dist: Distance >=0.1.3
Requires-Dist: numpy >=1.16.2
Requires-Dist: environs >=8.0.0
Requires-Dist: joblib >=0.15.1
Requires-Dist: scikit-learn >=0.23.1
